ICS_IPA/DSRTools.py
ICS_IPA/DataFileIO-32.dll
ICS_IPA/DataFileIO-64.dll
ICS_IPA/DataFileIOLibrary.py
ICS_IPA/DataFileIOLibraryInterface.py
ICS_IPA/IPAInterfaceLibrary.py
ICS_IPA/_DataFileIOLibraryInterface.so
ICS_IPA/__init__.py
ICS_IPA-0.4.52.dist-info/METADATA
ICS_IPA-0.4.52.dist-info/WHEEL
ICS_IPA-0.4.52.dist-info/top_level.txt
ICS_IPA-0.4.52.dist-info/RECORD
