Metadata-Version: 2.1
Name: ICS-IPA
Version: 0.4.52
Summary: 64bit API used for DataMining mdf data files using DataSpy
Home-page: https://github.com/intrepidcs/ICS_IPA
Maintainer: Zaid Nackasha
Maintainer-email: ZNackasha@intrepidcs.com
License: UNKNOWN
Download-URL: https://github.com/intrepidcs/ICS_IPA/archive/0.4.52.tar.gz
Platform: UNKNOWN
